fakejson/__init__.py
fakejson/main.py
fakejson/parser/__init__.py
fakejson/parser/exceptions.py
fakejson/parser/parser.py
fakejson-0.9.1.dist-info/METADATA
fakejson-0.9.1.dist-info/WHEEL
fakejson-0.9.1.dist-info/licenses/LICENSE
fakejson-0.9.1.dist-info/RECORD
