Metadata-Version: 2.1
Name: fakejson
Version: 0.9.1
Summary: json-like format(allowing single-quote string) parser
Project-URL: Homepage, https://github.com/kokardy/fakejson
Project-URL: Bug Tracker, https://github.com/kokardy/fakejson/issues
Author-email: kokardy <mgc1028@gmail.com>
License-File: LICENSE
Classifier: License :: OSI Approved :: MIT License
Classifier: Operating System :: OS Independent
Classifier: Programming Language :: Python :: 3
Requires-Python: >=3.10
